{"id":"OP05-069_p2","pack_id":"569105","name":"Trafalgar Law","rarity":"SuperRare","category":"Character","img_url":"../images/cardlist/card/OP05-069_p2.png?251017","img_full_url":"https://en.onepiece-cardgame.com/images/cardlist/card/OP05-069_p2.png?251017","colors":["Purple"],"cost":3,"attributes":["Slash"],"power":5000,"counter":null,"types":["Heart Pirates"],"effect":"[When Attacking] If your opponent has more DON!! cards on their field than you, look at 5 cards from the top of your deck; reveal up to 1 {Heart Pirates} type card and add it to your hand. Then, place the rest at the bottom of your deck in any order.","trigger":null}