{"id":"OP05-027","pack_id":"569105","name":"Trafalgar Law","rarity":"Uncommon","category":"Character","img_url":"../images/cardlist/card/OP05-027.png?251017","img_full_url":"https://en.onepiece-cardgame.com/images/cardlist/card/OP05-027.png?251017","colors":["Green"],"cost":1,"attributes":["Wisdom"],"power":2000,"counter":1000,"types":["Donquixote Pirates"],"effect":"[Activate: Main] You may trash this Character: Rest up to 1 of your opponent's Characters with a cost of 3 or less.","trigger":null}