{"id":"OP05-043_p1","pack_id":"569105","name":"Ulti","rarity":"SuperRare","category":"Character","img_url":"../images/cardlist/card/OP05-043_p1.png?251017","img_full_url":"https://en.onepiece-cardgame.com/images/cardlist/card/OP05-043_p1.png?251017","colors":["Blue"],"cost":4,"attributes":["Strike"],"power":5000,"counter":1000,"types":["Animal Kingdom Pirates"],"effect":"[On Play] If your Leader is multicolored, look at 3 cards from the top of your deck and add up to 1 card to your hand. Then, place the rest at the top or bottom of the deck in any order.","trigger":null}