{"id":"OP06-040","pack_id":"569106","name":"Shark Arrows","rarity":"Common","category":"Event","img_url":"../images/cardlist/card/OP06-040.png?251017","img_full_url":"https://en.onepiece-cardgame.com/images/cardlist/card/OP06-040.png?251017","colors":["Green"],"cost":2,"attributes":[],"power":null,"counter":null,"types":["Fish-Man","New Fish-Man Pirates"],"effect":"[Main] K.O. up to 2 of your opponent's rested Characters with a cost of 3 or less.","trigger":"[Trigger] Activate this card's [Main] effect."}