{"id":"OP01-067","pack_id":"569101","name":"Crocodile","rarity":"SuperRare","category":"Character","img_url":"../images/cardlist/card/OP01-067.png?251017","img_full_url":"https://en.onepiece-cardgame.com/images/cardlist/card/OP01-067.png?251017","colors":["Blue"],"cost":7,"attributes":["Special"],"power":7000,"counter":1000,"types":["The Seven Warlords of the Sea","Baroque Works"],"effect":"[Banish] (When this card deals damage, the target card is trashed without activating its Trigger.)<br>[DON!! x1] Give blue Events in your hand −1 cost.","trigger":null}