{"id":"EB02-046","pack_id":"569202","name":"Hildon","rarity":"Common","category":"Character","img_url":"../images/cardlist/card/EB02-046.png?251017","img_full_url":"https://en.onepiece-cardgame.com/images/cardlist/card/EB02-046.png?251017","colors":["Black"],"cost":3,"attributes":["Wisdom"],"power":3000,"counter":2000,"types":["Thriller Bark Pirates"],"effect":"[On Play] Trash 2 cards from the top of your deck and give up to 1 of your opponent's Characters −1 cost during this turn.","trigger":null}