{"id":"ST05-010","pack_id":"569005","name":"Zephyr","rarity":"Common","category":"Character","img_url":"../images/cardlist/card/ST05-010.png?251017","img_full_url":"https://en.onepiece-cardgame.com/images/cardlist/card/ST05-010.png?251017","colors":["Purple"],"cost":7,"attributes":["Strike"],"power":8000,"counter":null,"types":["FILM","Neo Navy"],"effect":"When this Character battles ＜Strike＞ attribute Characters, this Character gains +3000 power during this turn.<br>[Activate: Main] [Once Per Turn] DON!! −1 (You may return the specified number of DON!! cards from your field to your DON!! deck.): This Character gains +2000 power during this turn.","trigger":null}