{"id":"OP10-072","pack_id":"569110","name":"Donquixote Rosinante","rarity":"SuperRare","category":"Character","img_url":"../images/cardlist/card/OP10-072.png?251017","img_full_url":"https://en.onepiece-cardgame.com/images/cardlist/card/OP10-072.png?251017","colors":["Purple"],"cost":5,"attributes":["Special"],"power":6000,"counter":1000,"types":["Navy","Donquixote Pirates"],"effect":"[On Play] You may trash 1 Event from your hand: Draw 2 cards.<br>[End of Your Turn] If you have 7 or more DON!! cards on your field, set up to 2 of your DON!! cards as active.","trigger":null}