{"id":"OP10-103","pack_id":"569110","name":"Capone\"Gang\"Bege","rarity":"Rare","category":"Character","img_url":"../images/cardlist/card/OP10-103.png?251017","img_full_url":"https://en.onepiece-cardgame.com/images/cardlist/card/OP10-103.png?251017","colors":["Yellow"],"cost":1,"attributes":["Ranged"],"power":null,"counter":2000,"types":["Supernovas","Firetank Pirates"],"effect":"[On Play] You may add 1 card from the top or bottom of your Life cards to your hand: Add up to 1 {Supernovas} type Character card from your hand to the top of your Life cards face-up.","trigger":null}