{"id":"EB04-033","pack_id":"569114","name":"Groggy Monsters","rarity":"Common","category":"Character","img_url":"../images/cardlist/card/EB04-033.png?260305","img_full_url":"https://en.onepiece-cardgame.com/images/cardlist/card/EB04-033.png?260305","cost":5,"attributes":["Strike"],"power":6000,"counter":1000,"colors":["Purple"],"block_number":4,"types":["Giant","Fish-Man","Foxy Pirates"],"effect":"[On Play] DON!! −1: If you have 3 or more {Foxy Pirates} type Characters, K.O. up to 1 of your opponent's Characters with 6000 base power or less.","trigger":null}