{"id":"OP14-084","pack_id":"569114","name":"Ms. All Sunday","rarity":"SuperRare","category":"Character","img_url":"../images/cardlist/card/OP14-084.png?260305","img_full_url":"https://en.onepiece-cardgame.com/images/cardlist/card/OP14-084.png?260305","cost":7,"attributes":["Strike"],"power":8000,"counter":null,"colors":["Black"],"block_number":4,"types":["Baroque Works"],"effect":"[On Play] If your Leader's type includes \"Baroque Works\", play up to 1 Character card with a type including \"Baroque Works\" and a cost of 4 or less and up to 1 Character card with a type including \"Baroque Works\" and a cost of 1 from your trash.","trigger":null}