{"id":"P-077_p2","pack_id":"569901","name":"Ulti","rarity":"Promo","category":"Character","img_url":"../images/cardlist/card/P-077_p2.png?251017","img_full_url":"https://en.onepiece-cardgame.com/images/cardlist/card/P-077_p2.png?251017","colors":["Purple"],"cost":6,"attributes":["Strike"],"power":6000,"counter":1000,"types":["Animal Kingdom Pirates"],"effect":"[Once Per Turn] When 2 or more DON!! cards on your field are returned to your DON!! deck, add up to 1 DON!! card from your DON!! deck and rest it. Then, set up to 1 of your purple Stages as active.","trigger":null}