{"id":"OP11-067","pack_id":"569111","name":"Charlotte Katakuri","rarity":"SuperRare","category":"Character","img_url":"../images/cardlist/card/OP11-067.png?251017","img_full_url":"https://en.onepiece-cardgame.com/images/cardlist/card/OP11-067.png?251017","colors":["Purple"],"cost":8,"attributes":["Strike"],"power":8000,"counter":null,"types":["Big Mom Pirates"],"effect":"[Blocker]<br>[End of Your Turn] Set up to 2 of your {Big Mom Pirates} type Characters with a cost of 3 or more as active. Then, add up to 1 DON!! card from your DON!! deck and rest it.","trigger":null}