{"id":"P-014_p2","pack_id":"569301","name":"Koby","rarity":"Promo","category":"Character","img_url":"../images/cardlist/card/P-014_p2.png?251017","img_full_url":"https://en.onepiece-cardgame.com/images/cardlist/card/P-014_p2.png?251017","colors":["Red"],"cost":3,"attributes":["Strike"],"power":3000,"counter":null,"types":["FILM","Navy"],"effect":"[Blocker] (After your opponent declares an attack, you may rest this card to make it the new target of the attack.)","trigger":"[Trigger] Play this card."}