{"id":"OP02-085_p1","pack_id":"569102","name":"Magellan","rarity":"SuperRare","category":"Character","img_url":"../images/cardlist/card/OP02-085_p1.png?251017","img_full_url":"https://en.onepiece-cardgame.com/images/cardlist/card/OP02-085_p1.png?251017","colors":["Purple"],"cost":5,"attributes":["Special"],"power":6000,"counter":null,"types":["Impel Down"],"effect":"[On Play] DON!! −1 (You may return the specified number of DON!! cards from your field to your DON!! deck.): Your opponent returns 1 DON!! card from their field to their DON!! deck.<br>[Opponent's Turn] When this Character is K.O.'d, your opponent returns 2 DON!! cards from their field to their DON!! deck.","trigger":null}